{
	"name": "MetadataDrivenCopyTask_60m_DestinationDS",
	"properties": {
		"linkedServiceName": {
			"referenceName": "AzureBlobStorageLS",
			"type": "LinkedServiceReference"
		},
		"parameters": {
			"cw_fileName": {
				"type": "String"
			},
			"cw_folderPath": {
				"type": "Object"
			},
			"cw_container": {
				"type": "String"
			}
		},
		"folder": {
			"name": "MetadataDrivenCopyTask_60m_20260305"
		},
		"annotations": [],
		"type": "Parquet",
		"typeProperties": {
			"location": {
				"type": "AzureBlobStorageLocation",
				"fileName": {
					"value": "@dataset().cw_fileName",
					"type": "Expression"
				},
				"folderPath": {
					"value": "@dataset().cw_folderPath",
					"type": "Expression"
				},
				"container": {
					"value": "@dataset().cw_container",
					"type": "Expression"
				}
			},
			"compressionCodec": "snappy"
		},
		"schema": []
	},
	"type": "Microsoft.DataFactory/factories/datasets"
}